README.txt
setup.py
nodebox/__init__.py
nodebox/ext/__init__.py
nodebox/ext/setup.py
nodebox/ext/psyco/__init__.py
nodebox/ext/psyco/classes.py
nodebox/ext/psyco/core.py
nodebox/ext/psyco/kdictproxy.py
nodebox/ext/psyco/logger.py
nodebox/ext/psyco/profiler.py
nodebox/ext/psyco/support.py
nodebox/graphics/__init__.py
nodebox/graphics/bezier.py
nodebox/graphics/context.py
nodebox/graphics/geometry.py
nodebox/graphics/noise.py
nodebox/graphics/physics.py
nodebox/graphics/shader.py
nodebox/gui/__init__.py
nodebox/gui/controls.py
nodebox/sound/__init__.py
nodebox/sound/osc.py
nodebox/sound/process.py
nodebox_opengl.egg-info/PKG-INFO
nodebox_opengl.egg-info/SOURCES.txt
nodebox_opengl.egg-info/dependency_links.txt
nodebox_opengl.egg-info/requires.txt
nodebox_opengl.egg-info/top_level.txt