Metadata-Version: 1.0
Name: nodebox-opengl
Version: 1.6.1
Summary: NodeBox for OpenGL is a free, cross-platform library for generating 2D animations with Python programming code.
Home-page: http://www.cityinabottle.org/nodebox/
Author: Tom De Smedt, Frederik De Bleser
Author-email: UNKNOWN
License: BSD
Keywords: 2d graphics sound physics games multimedia
Platform: UNKNOWN
Classifier: Development Status :: 4 - Beta
Classifier: Environment :: MacOS X
Classifier: Environment :: Win32 (MS Windows)
Classifier: Environment :: X11 Applications
Classifier: Intended Audience :: Developers
Classifier: Intended Audience :: Education
Classifier: License :: OSI Approved :: BSD License
Classifier: Operating System :: MacOS :: MacOS X
Classifier: Operating System :: Microsoft :: Windows
Classifier: Operating System :: POSIX :: Linux
Classifier: Programming Language :: Python
Classifier: Topic :: Artistic Software
Classifier: Topic :: Games/Entertainment
Classifier: Topic :: Multimedia :: Graphics
Classifier: Topic :: Software Development :: Libraries :: Python Modules
